<?xml version=\"1.0\" encoding=\"UTF-8\"?><SOAP-ENV:Envelope SOAP-ENV:encodingStyle=\"http://schemas.xmlsoap.org/soap/encoding/\" xmlns:SOAP-ENV=\"http://schemas.xmlsoap.org/soap/envelope/\" xmlns:xsd=\"http://www.w3.org/2001/XMLSchema\" xmlns:xsi=\"http://www.w3.org/2001/XMLSchema-instance\" xmlns:SOAP-ENC=\"http://schemas.xmlsoap.org/soap/encoding/\" xmlns:tns=\"CRS\"><SOAP-ENV:Body><ns1:receiverAddResponse xmlns:ns1=\"CRS\"><return xsi:type=\"tns:returnReceiver\"><status xsi:type=\"xsd:string\">SUCCESS</status><message xsi:type=\"xsd:string\"></message><statuscode xsi:type=\"xsd:int\">0</statuscode><data xsi:type=\"tns:receiverData\"><id xsi:type=\"xsd:int\">5390</id><email xsi:type=\"xsd:string\">foo@bar.com</email><registered xsi:type=\"xsd:int\">1400041026</registered><activated xsi:type=\"xsd:int\">1400041026</activated><deactivated xsi:type=\"xsd:int\">0</deactivated><active xsi:type=\"xsd:boolean\">true</active><source xsi:type=\"xsd:string\">API</source><quality xsi:type=\"xsd:int\">0</quality></data></return></ns1:receiverAddResponse></SOAP-ENV:Body></SOAP-ENV:Envelope>